codemark/__init__.py
codemark/__main__.py
codemark/pyrustic_data/backstage/config/build.json
codemark/pyrustic_data/backstage/config/init.json
codemark/pyrustic_data/backstage/config/release.json
codemark/pyrustic_data/backstage/data/github_release_form.json
codemark/pyrustic_data/backstage/report/build_report.json
codemark/pyrustic_data/backstage/report/release_report.json
codemark/pyrustic_data/hubstore/img.json
codemark/pyrustic_data/hubstore/promotion.json
tests/__init__.py
codemark-0.0.1.dist-info/LICENSE
codemark-0.0.1.dist-info/METADATA
codemark-0.0.1.dist-info/WHEEL
codemark-0.0.1.dist-info/entry_points.txt
codemark-0.0.1.dist-info/top_level.txt
codemark-0.0.1.dist-info/RECORD
